uml_generator/__init__.py
uml_generator/main.py
uml_class_diagram_generator-0.1.dist-info/LICENSE
uml_class_diagram_generator-0.1.dist-info/METADATA
uml_class_diagram_generator-0.1.dist-info/WHEEL
uml_class_diagram_generator-0.1.dist-info/entry_points.txt
uml_class_diagram_generator-0.1.dist-info/top_level.txt
uml_class_diagram_generator-0.1.dist-info/RECORD
