Metadata-Version: 2.1
Name: uml-class-diagram-generator
Version: 0.1
Summary: A tool to generate UML Class Diagrams from Python source code.
Home-page: https://github.com/siddharthverma-1607/uml-class-diagram-generator.git
Author: Siddharth Verma
Author-email: siddharthverma.er.cse@gmail.com
Classifier: Programming Language :: Python :: 3
Classifier: License :: OSI Approved :: MIT License
Classifier: Operating System :: OS Independent
Requires-Python: >=3.6
License-File: LICENSE
